asyncmetrics/__init__.py
asyncmetrics/graphite.py
asyncmetrics/metric.py
asyncmetrics/protocols/__init__.py
asyncmetrics/protocols/gzip.py
asyncmetrics/protocols/gziptcp.py
asyncmetrics/protocols/gziptcpssl.py
asyncmetrics/protocols/plain.py
asyncmetrics/protocols/plaintcp.py
asyncmetrics/protocols/plaintcpssl.py
asyncmetrics/protocols/plainudp.py
asyncmetrics/protocols/protocol.py
asyncmetrics/protocols/protocolerror.py
asyncmetrics/protocols/tcp.py
asyncmetrics/protocols/tcpssl.py
asyncmetrics/protocols/udp.py
asyncmetrics-0.4.0.dist-info/LICENSE
asyncmetrics-0.4.0.dist-info/METADATA
asyncmetrics-0.4.0.dist-info/WHEEL
asyncmetrics-0.4.0.dist-info/top_level.txt
asyncmetrics-0.4.0.dist-info/RECORD
