Metadata-Version: 2.1
Name: asyncmetrics
Version: 0.4.0
Summary: Send metrics to Graphite asynchronously from your asyncio application
Home-page: https://github.com/mon4ter/asyncmetrics
Author: Dmitry Galkin
Author-email: mon4ter@gmail.com
License: MIT
Platform: UNKNOWN
Classifier: Development Status :: 4 - Beta
Classifier: Programming Language :: Python :: 3.5
Classifier: Programming Language :: Python :: 3.6
Classifier: Programming Language :: Python :: 3.7
Classifier: Programming Language :: Python :: 3.8
Classifier: Programming Language :: Python :: 3.9
Classifier: License :: OSI Approved :: MIT License
Classifier: Operating System :: OS Independent
